[{"_path":"/travel/japan","_dir":"travel","_draft":false,"_partial":false,"_locale":"","_empty":false,"title":"2022箱根河口湖","description":"五天四夜使用大眾運輸玩箱根河口湖","id":"2022j","draft":true,"head":{"meta":[{"name":"keywords","content":"日本, 2023"}]},"tags":["旅行相關","2023東京河口湖箱根"],"_type":"markdown","_id":"content:1.travel:6.japan.md","_source":"content","_file":"1.travel/6.japan.md","_extension":"md"},{"_path":"/blog/separate_account","_dir":"blog","_draft":false,"_partial":false,"_locale":"","_empty":false,"title":"使用分離帳戶理財","description":"一直沒有辦法持續記帳，透過使用分離帳戶來理財。","id":"20230316","draft":false,"head":[{"name":"og:title","content":"使用分離帳戶理財 | IngridKao blog"}],"modified":"2023-03-30","tags":["理財相關"],"_type":"markdown","_id":"content:2.blog:2.separate_account.md","_source":"content","_file":"2.blog/2.separate_account.md","_extension":"md"}]