[{"_path":"/blog","_dir":"","_draft":false,"_partial":false,"_locale":"","_empty":false,"title":"blog","description":"This page is using the layouts/blog.vue layout.","layout":"blog","_type":"markdown","_id":"content:blog.md","_source":"content","_file":"blog.md","_extension":"md"},{"_path":"/investment","_dir":"","_draft":false,"_partial":false,"_locale":"","_empty":false,"title":"investment","description":"This page is using the layouts/investment.vue layout.","layout":"investment","_type":"markdown","_id":"content:investment.md","_source":"content","_file":"investment.md","_extension":"md"}]