{"_path":"/travel/singapore_food","_dir":"travel","_draft":false,"_partial":false,"_locale":"","_empty":false,"title":"新加坡食記","description":"2023二月新加坡食記","id":"2023s5","draft":true,"head":{"meta":[{"name":"keywords","content":"食記, 車馬水"}]},"modified":"2023-02-04","tags":["旅行相關","2023新加坡自由行"],"body":{"type":"root","children":[{"type":"element","tag":"p","props":{},"children":[{"type":"text","value":"可能是因為疫情關係，新加坡的資料大多都停留在2020以前，這邊記錄一些行前查詢的項目。"}]},{"type":"element","tag":"blockquote","props":{},"children":[]},{"type":"element","tag":"h2","props":{"id":"五星必吃"},"children":[{"type":"text","value":"五星必吃"}]},{"type":"element","tag":"blockquote","props":{},"children":[{"type":"element","tag":"p","props":{},"children":[{"type":"text","value":"因為防疫規定依據時間修正，這邊的紀錄是2022二月的規定\n小地圖"}]}]},{"type":"element","tag":"h2","props":{"id":"有名但覺得普普"},"children":[{"type":"text","value":"有名但覺得普普"}]},{"type":"element","tag":"ol","props":{},"children":[{"type":"element","tag":"li","props":{},"children":[{"type":"text","value":"台新Flygo(Mastercard)"},{"type":"element","tag":"ul","props":{},"children":[{"type":"element","tag":"li","props":{},"children":[{"type":"text","value":"海外"},{"type":"element","tag":"strong","props":{},"children":[{"type":"text","value":"3"}]},{"type":"text","value":"%無上限"}]},{"type":"element","tag":"li","props":{},"children":[{"type":"text","value":"海外交易手續費1.5%的手續費(現金回饋就可以抵消)"}]},{"type":"element","tag":"li","props":{},"children":[{"type":"text","value":"付全程交通如機票享旅遊平安險"}]},{"type":"element","tag":"li","props":{},"children":[{"type":"text","value":"行前問了一下剛從新加坡回國的友人，需不需要買交通卡，他覺得如果沒有做太多大眾運輸可以用信用卡買單程車票，只是會被收海外交易手續費大約1台幣，建議用Mastercard手續會便宜一點(結算方式的關係)；不過就沒有交通卡的優惠\n"},{"type":"element","tag":"a","props":{"href":"https://www.bring-you.info/zh-tw/singapore_smrt","rel":["nofollow"]},"children":[{"type":"text","value":"【參考BringYou】搭地鐵玩遍新加坡景點、怎麼從樟宜機場搭地鐵到市區、信用卡進站使用注意事項"}]}]}]}]},{"type":"element","tag":"li","props":{},"children":[{"type":"text","value":"台新gogoro(visa)⇒累積消費$5,000 元"},{"type":"element","tag":"ul","props":{},"children":[{"type":"element","tag":"li","props":{},"children":[{"type":"text","value":"海外"},{"type":"element","tag":"strong","props":{},"children":[{"type":"text","value":"3"}]},{"type":"text","value":"%無上限"}]},{"type":"element","tag":"li","props":{},"children":[{"type":"text","value":"海外交易手續費1.5%的手續費(現金回饋就可以抵消)"}]}]}]}]},{"type":"element","tag":"h2","props":{"id":"不是很適合自己"},"children":[{"type":"text","value":"不是很適合自己"}]},{"type":"element","tag":"hr","props":{},"children":[]},{"type":"element","tag":"h3","props":{"id":"相關文章"},"children":[{"type":"text","value":"相關文章"}]},{"type":"element","tag":"ul","props":{},"children":[{"type":"element","tag":"li","props":{},"children":[{"type":"element","tag":"a","props":{"href":"/travel/singapore_preparation"},"children":[{"type":"text","value":"入境及進入市區交通"}]}]},{"type":"element","tag":"li","props":{},"children":[{"type":"element","tag":"a","props":{"href":"/travel/singapore_hotel"},"children":[{"type":"text","value":"新加坡住宿-牛車水及克拉碼頭"}]}]},{"type":"element","tag":"li","props":{},"children":[{"type":"element","tag":"a","props":{"href":"/travel/singapore_spot"},"children":[{"type":"text","value":"景點安排及紀錄"}]}]},{"type":"element","tag":"li","props":{},"children":[{"type":"element","tag":"a","props":{"href":"/travel/singapore_zone1"},"children":[{"type":"text","value":"新加坡濱海灣花園及金沙酒店"}]}]}]}],"toc":{"title":"","searchDepth":2,"depth":2,"links":[{"id":"五星必吃","depth":2,"text":"五星必吃"},{"id":"有名但覺得普普","depth":2,"text":"有名但覺得普普"},{"id":"不是很適合自己","depth":2,"text":"不是很適合自己","children":[{"id":"相關文章","depth":3,"text":"相關文章"}]}]}},"_type":"markdown","_id":"content:travel:6.singapore_food.md","_source":"content","_file":"travel/6.singapore_food.md","_extension":"md"}